pylint_restricted_imports/__init__.py
pylint_restricted_imports-0.2.2.dist-info/LICENSE
pylint_restricted_imports-0.2.2.dist-info/METADATA
pylint_restricted_imports-0.2.2.dist-info/WHEEL
pylint_restricted_imports-0.2.2.dist-info/RECORD
