Metadata-Version: 2.1
Name: pylint-restricted-imports
Version: 0.2.2
Summary: pylint-restricted-imports is a Pylint plugin to restrict what imports are allowed in different modules
Home-page: https://github.com/pexip/pylint-restricted-imports
License: MIT
Keywords: pylint,plugin,imports
Author: Pexip AS
Author-email: packaging@pexip.com
Requires-Python: >=3.8,<4.0
Classifier: Environment :: Console
Classifier: Intended Audience :: Developers
Classifier: License :: OSI Approved :: MIT License
Classifier: Programming Language :: Python :: 3
Classifier: Programming Language :: Python :: 3.8
Classifier: Programming Language :: Python :: 3.9
Classifier: Programming Language :: Python :: 3.10
Classifier: Programming Language :: Python :: 3.11
Classifier: Programming Language :: Python :: 3.12
Classifier: Topic :: Software Development :: Quality Assurance
Requires-Dist: astroid (>=1.0)
Requires-Dist: pylint (>=2.16)
Project-URL: Repository, https://github.com/pexip/pylint-restricted-imports
